guan/AI_chat.py
guan/Fourier_transform.py
guan/Green_functions.py
guan/Hamiltonian_of_examples.py
guan/__init__.py
guan/band_structures_and_wave_functions.py
guan/basic_functions.py
guan/data_processing.py
guan/decorators.py
guan/density_of_states.py
guan/figure_plotting.py
guan/file_reading_and_writing.py
guan/machine_learning.py
guan/others.py
guan/quantum_transport.py
guan/topological_invariant.py
guan-0.1.200.dist-info/licenses/LICENSE
guan-0.1.200.dist-info/METADATA
guan-0.1.200.dist-info/WHEEL
guan-0.1.200.dist-info/top_level.txt
guan-0.1.200.dist-info/RECORD
