Metadata-Version: 2.4
Name: guan
Version: 0.1.200
Summary: An open source python package
Home-page: https://py.guanjihuan.com
Author: guanjihuan
Author-email: guanjihuan@163.com
Project-URL: Bug Tracker, https://py.guanjihuan.com
Classifier: Programming Language :: Python :: 3
Classifier: License :: OSI Approved :: MIT License
Classifier: Operating System :: OS Independent
Requires-Python: >=3.6
License-File: LICENSE
Dynamic: license-file
